swapper/__init__.py
swapper-1.3.0.dist-info/LICENSE
swapper-1.3.0.dist-info/METADATA
swapper-1.3.0.dist-info/WHEEL
swapper-1.3.0.dist-info/top_level.txt
swapper-1.3.0.dist-info/RECORD
